LICENSE
MANIFEST.in
README.md
requirements.json
setup.py
lazydock_md_task/__init__.py
lazydock_md_task/__version__.py
lazydock_md_task/cli.py
lazydock_md_task/sdrms.py
lazydock_md_task/trajectory.py
lazydock_md_task/utils.py
lazydock_md_task.egg-info/PKG-INFO
lazydock_md_task.egg-info/SOURCES.txt
lazydock_md_task.egg-info/dependency_links.txt
lazydock_md_task.egg-info/requires.txt
lazydock_md_task.egg-info/top_level.txt
lazydock_md_task/scripts/__init__.py
lazydock_md_task/scripts/avg_network.py
lazydock_md_task/scripts/calc_correlation.py
lazydock_md_task/scripts/calc_delta.py
lazydock_md_task/scripts/calc_delta_BC.py
lazydock_md_task/scripts/calc_delta_L.py
lazydock_md_task/scripts/calc_network.py
lazydock_md_task/scripts/compare_networks.py
lazydock_md_task/scripts/contact_map.py
lazydock_md_task/scripts/contact_map_v2.py
lazydock_md_task/scripts/dcc_subsection.py
lazydock_md_task/scripts/delta_networks.py
lazydock_md_task/scripts/prs.py
lazydock_md_task/scripts/prs_v2.py
lazydock_md_task/strategies/__init__.py
lazydock_md_task/strategies/normalization.py