Metadata-Version: 2.1
Name: lazydock_md_task
Version: 0.2.2
Summary: A Python package for molecular docking
Home-page: https://github.com/BHM-Bob/MD-TASK
Author: BHM-Bob G
Author-email: bhmfly@foxmail.com
License: GPL-3.0 License
Keywords: molecular docking,Utilities
Platform: any
Classifier: Development Status :: 4 - Beta
Classifier: Intended Audience :: Science/Research
Classifier: Topic :: Utilities
Classifier: License :: OSI Approved :: GNU General Public License v3 (GPLv3)
Classifier: Programming Language :: Python :: 3
Classifier: Programming Language :: Python :: 3.8
Classifier: Programming Language :: Python :: 3.9
Classifier: Programming Language :: Python :: 3.10
Classifier: Programming Language :: Python :: 3.11
Classifier: Programming Language :: Python :: 3.12
Requires-Python: >=3.8, <3.13
License-File: LICENSE
Requires-Dist: mbapy>=0.10.5
Requires-Dist: networkx>=3
Requires-Dist: DuIvyTools>=0.6.0
Requires-Dist: mdtraj
Requires-Dist: natsort
